odoo/addons/ssi_partner_experience/README.rst
odoo/addons/ssi_partner_experience/__init__.py
odoo/addons/ssi_partner_experience/__manifest__.py
odoo/addons/ssi_partner_experience/menu.xml
odoo/addons/ssi_partner_experience/models/__init__.py
odoo/addons/ssi_partner_experience/models/partner_academic.py
odoo/addons/ssi_partner_experience/models/partner_certification.py
odoo/addons/ssi_partner_experience/models/partner_experience.py
odoo/addons/ssi_partner_experience/models/partner_experience_mixin.py
odoo/addons/ssi_partner_experience/models/res_partner.py
odoo/addons/ssi_partner_experience/security/ir.model.access.csv
odoo/addons/ssi_partner_experience/security/res_group_data.xml
odoo/addons/ssi_partner_experience/static/description/icon.png
odoo/addons/ssi_partner_experience/views/partner_academic_view.xml
odoo/addons/ssi_partner_experience/views/partner_certification_view.xml
odoo/addons/ssi_partner_experience/views/partner_experience_view.xml
odoo/addons/ssi_partner_experience/views/res_partner_views.xml
odoo14_addon_ssi_partner_experience-14.0.1.2.0.dist-info/METADATA
odoo14_addon_ssi_partner_experience-14.0.1.2.0.dist-info/WHEEL
odoo14_addon_ssi_partner_experience-14.0.1.2.0.dist-info/top_level.txt
odoo14_addon_ssi_partner_experience-14.0.1.2.0.dist-info/RECORD
